autoimpute/__init__.py
autoimpute/__version__.py
autoimpute/analysis/__init__.py
autoimpute/analysis/base_regressor.py
autoimpute/analysis/linear_regressor.py
autoimpute/analysis/logistic_regressor.py
autoimpute/analysis/metrics.py
autoimpute/imputations/__init__.py
autoimpute/imputations/deletion.py
autoimpute/imputations/errors.py
autoimpute/imputations/helpers.py
autoimpute/imputations/method_names.py
autoimpute/imputations/mis_classifier.py
autoimpute/imputations/dataframe/__init__.py
autoimpute/imputations/dataframe/base_imputer.py
autoimpute/imputations/dataframe/mice_imputer.py
autoimpute/imputations/dataframe/multiple_imputer.py
autoimpute/imputations/dataframe/single_imputer.py
autoimpute/imputations/series/__init__.py
autoimpute/imputations/series/base.py
autoimpute/imputations/series/bayesian_regression.py
autoimpute/imputations/series/categorical.py
autoimpute/imputations/series/default.py
autoimpute/imputations/series/ffill.py
autoimpute/imputations/series/interpolation.py
autoimpute/imputations/series/linear_regression.py
autoimpute/imputations/series/logistic_regression.py
autoimpute/imputations/series/lrd.py
autoimpute/imputations/series/mean.py
autoimpute/imputations/series/median.py
autoimpute/imputations/series/mode.py
autoimpute/imputations/series/norm.py
autoimpute/imputations/series/norm_unit_variance.py
autoimpute/imputations/series/pmm.py
autoimpute/imputations/series/random.py
autoimpute/utils/__init__.py
autoimpute/utils/checks.py
autoimpute/utils/dataframes.py
autoimpute/utils/helpers.py
autoimpute/utils/patterns.py
autoimpute/visuals/__init__.py
autoimpute/visuals/helpers.py
autoimpute/visuals/imputations.py
autoimpute/visuals/utils.py
tests/test_imputations/__init__.py
tests/test_imputations/test_mice_imputer.py
tests/test_imputations/test_missingness_classifier.py
tests/test_imputations/test_single_imputer.py
tests/test_utils/__init__.py
tests/test_utils/test_checks.py
tests/test_utils/test_patterns.py
tests/test_visuals/__init__.py
autoimpute-0.14.1.dist-info/LICENSE
autoimpute-0.14.1.dist-info/METADATA
autoimpute-0.14.1.dist-info/WHEEL
autoimpute-0.14.1.dist-info/top_level.txt
autoimpute-0.14.1.dist-info/RECORD
