Metadata-Version: 2.1
Name: autoimpute
Version: 0.14.1
Summary: Imputation Methods in Python
Home-page: https://github.com/kearnz/autoimpute
Author: Joseph Kearney, Shahid Barkat
Author-email: josephkearney14@gmail.com, shahidbarkat@gmail.com
License: MIT
Classifier: Development Status :: 3 - Alpha
Classifier: Intended Audience :: Science/Research
Classifier: Intended Audience :: Developers
Classifier: License :: OSI Approved :: MIT License
Classifier: Programming Language :: Python
Classifier: Programming Language :: Python :: 3
Classifier: Programming Language :: Python :: 3.8
Classifier: Programming Language :: Python :: 3.9
Classifier: Operating System :: OS Independent
Classifier: Topic :: Software Development
Classifier: Topic :: Scientific/Engineering
Requires-Python: >=3.8.0
License-File: LICENSE
Requires-Dist: numpy
Requires-Dist: scipy
Requires-Dist: pandas
Requires-Dist: statsmodels
Requires-Dist: xgboost
Requires-Dist: scikit-learn
Requires-Dist: pymc
Requires-Dist: seaborn
Requires-Dist: missingno
